{
"autoplayBgm":false,"autoplayBgs":false,"battleback1Name":"","battleback2Name":"","bgm":{"name":"","pan":0,"pitch":100,"volume":90},"bgs":{"name":"","pan":0,"pitch":100,"volume":90},"disableDashing":false,"displayName":"","encounterList":[],"encounterStep":30,"height":13,"note":"","parallaxLoopX":false,"parallaxLoopY":false,"parallaxName":"","parallaxShow":true,"parallaxSx":0,"parallaxSy":0,"scrollType":0,"specifyBattleback":false,"tilesetId":1,"width":17,
"data":[0,0,0,0,0,0,0,0,0,0,0,0,0,0,0,0,0,0,0,0,0,0,0,0,0,0,0,0,0,0,0,0,0,0,0,0,0,0,0,0,0,0,0,0,0,0,0,0,0,0,0,0,0,0,0,0,0,0,0,0,0,0,0,0,0,0,0,0,0,0,0,0,0,0,0,0,0,0,0,0,0,0,0,0,0,0,0,0,0,0,0,0,0,0,0,0,0,0,0,0,0,0,0,0,0,0,0,0,0,0,0,0,0,0,0,0,0,0,0,0,0,0,0,0,0,0,0,0,0,0,0,0,0,0,0,0,0,0,0,0,0,0,0,0,0,0,0,0,0,0,0,0,0,0,0,0,0,0,0,0,0,0,0,0,0,0,0,0,0,0,0,0,0,0,0,0,0,0,0,0,0,0,0,0,0,0,0,0,0,0,0,0,0,0,0,0,0,0,0,0,0,0,0,0,0,0,0,0,0,0,0,0,0,0,0,0,0,0,0,0,0,0,0,0,0,0,0,0,0,0,0,0,0,0,0,0,0,0,0,0,0,0,0,0,0,0,0,0,0,0,0,0,0,0,0,0,0,0,0,0,0,0,0,0,0,0,0,0,0,0,0,0,0,0,0,0,0,0,0,0,0,0,0,0,0,0,0,0,0,0,0,0,0,0,0,0,0,0,0,0,0,0,0,0,0,0,0,0,0,0,0,0,0,0,0,0,0,0,0,0,0,0,0,0,0,0,0,0,0,0,0,0,0,0,0,0,0,0,0,0,0,0,0,0,0,0,0,0,0,0,0,0,0,0,0,0,0,0,0,0,0,0,0,0,0,0,0,0,0,0,0,0,0,0,0,0,0,0,0,0,0,0,0,0,0,0,0,0,0,0,0,0,0,0,0,0,0,0,0,0,0,0,0,0,0,0,0,0,0,0,0,0,0,0,0,0,0,0,0,0,0,0,0,0,0,0,0,0,0,0,0,0,0,0,0,0,0,0,0,0,0,0,0,0,0,0,0,0,0,0,0,0,0,0,0,0,0,0,0,0,0,0,0,0,0,0,0,0,0,0,0,0,0,0,0,0,0,0,0,0,0,0,0,0,0,0,0,0,0,0,0,0,0,0,0,0,0,0,0,0,0,0,0,0,0,0,0,0,0,0,0,0,0,0,0,0,0,0,0,0,0,0,0,0,0,0,0,0,0,0,0,0,0,0,0,0,0,0,0,0,0,0,0,0,0,0,0,0,0,0,0,0,0,0,0,0,0,0,0,0,0,0,0,0,0,0,0,0,0,0,0,0,0,0,0,0,0,0,0,0,0,0,0,0,0,0,0,0,0,0,0,0,0,0,0,0,0,0,0,0,0,0,0,0,0,0,0,0,0,0,0,0,0,0,0,0,0,0,0,0,0,0,0,0,0,0,0,0,0,0,0,0,0,0,0,0,0,0,0,0,0,0,0,0,0,0,0,0,0,0,0,0,0,0,0,0,0,0,0,0,0,0,0,0,0,0,0,0,0,0,0,0,0,0,0,0,0,0,0,0,0,0,0,0,0,0,0,0,0,0,0,0,0,0,0,0,0,0,0,0,0,0,0,0,0,0,0,0,0,0,0,0,0,0,0,0,0,0,0,0,0,0,0,0,0,0,0,0,0,0,0,0,0,0,0,0,0,0,0,0,0,0,0,0,0,0,0,0,0,0,0,0,0,0,0,0,0,0,0,0,0,0,0,0,0,0,0,0,0,0,0,0,0,0,0,0,0,0,0,0,0,0,0,0,0,0,0,0,0,0,0,0,0,0,0,0,0,0,0,0,0,0,0,0,0,0,0,0,0,0,0,0,0,0,0,0,0,0,0,0,0,0,0,0,0,0,0,0,0,0,0,0,0,0,0,0,0,0,0,0,0,0,0,0,0,0,0,0,0,0,0,0,0,0,0,0,0,0,0,0,0,0,0,0,0,0,0,0,0,0,0,0,0,0,0,0,0,0,0,0,0,0,0,0,0,0,0,0,0,0,0,0,0,0,0,0,0,0,0,0,0,0,0,0,0,0,0,0,0,0,0,0,0,0,0,0,0,0,0,0,0,0,0,0,0,0,0,0,0,0,0,0,0,0,0,0,0,0,0,0,0,0,0,0,0,0,0,0,0,0,0,0,0,0,0,0,0,0,0,0,0,0,0,0,0,0,0,0,0,0,0,0,0,0,0,0,0,0,0,0,0,0,0,0,0,0,0,0,0,0,0,0,0,0,0,0,0,0,0,0,0,0,0,0,0,0,0,0,0,0,0,0,0,0,0,0,0,0,0,0,0,0,0,0,0,0,0,0,0,0,0,0,0,0,0,0,0,0,0,0,0,0,0,0,0,0,0,0,0,0,0,0,0,0,0,0,0,0,0,0,0,0,0,0,0,0,0,0,0,0,0,0,0,0,0,0,0,0,0,0,0,0,0,0,0,0,0,0,0,0,0,0,0,0,0,0,0,0,0,0,0,0,0,0,0,0,0,0,0,0,0,0,0,0,0,0,0,0,0,0,0,0,0,0,0,0,0,0,0,0,0,0,0,0,0,0,0,0,0,0,0,0,0,0,0,0,0,0,0,0,0,0,0,0,0,0,0,0,0,0,0,0,0,0,0,0,0,0,0,0,0,0,0,0,0,0,0,0,0,0,0,0,0,0,0,0,0,0,0,0,0,0,0,0,0,0,0,0,0,0,0,0,0,0,0,0,0,0,0,0,0,0,0,0,0,0,0,0,0,0,0,0,0,0,0,0,0,0,0,0,0,0,0,0,0,0,0,0,0,0,0,0,0,0,0,0,0,0,0,0,0,0,0,0,0,0,0,0,0,0,0,0,0,0,0,0,0,0,0,0,0,0,0,0,0,0,0,0,0,0,0,0,0,0,0,0,0,0,0,0,0,0,0,0,0,0,0,0,0,0,0,0,0,0,0,0,0,0,0,0,0,0,0,0,0,0,0,0,0,0,0,0,0,0,0,0],
"events":[
null,
{"id":1,"name":"EV001","note":"","pages":[{"conditions":{"actorId":1,"actorValid":false,"itemId":1,"itemValid":false,"selfSwitchCh":"A","selfSwitchValid":false,"switch1Id":822,"switch1Valid":true,"switch2Id":1,"switch2Valid":false,"variableId":1,"variableValid":false,"variableValue":0},"directionFix":false,"image":{"characterIndex":0,"characterName":"","direction":2,"pattern":0,"tileId":0},"list":[{"code":117,"indent":0,"parameters":[18]},{"code":356,"indent":0,"parameters":["MSGSE TALK CLEAR"]},{"code":356,"indent":0,"parameters":["NameBoxReset"]},{"code":101,"indent":0,"parameters":["",0,2,1]},{"code":401,"indent":0,"parameters":["Как странно..."]},{"code":101,"indent":0,"parameters":["",0,2,1]},{"code":401,"indent":0,"parameters":["\\.Мне кажется, я что-то забыла..."]},{"code":101,"indent":0,"parameters":["",0,2,1]},{"code":401,"indent":0,"parameters":["\\.Что-то... очень, очень важное..."]},{"code":231,"indent":0,"parameters":[31,"cara2-2",1,0,408,312,100,100,0,0]},{"code":232,"indent":0,"parameters":[31,0,1,0,408,312,100,100,255,0,120,true]},{"code":101,"indent":0,"parameters":["",0,1,2]},{"code":401,"indent":0,"parameters":["Хэй, Кейджи, скажи мне, что."]},{"code":356,"indent":0,"parameters":["MSGSE TALK DEFAULT"]},{"code":231,"indent":0,"parameters":[31,"cara2-1",1,0,408,312,100,100,255,0]},{"code":250,"indent":0,"parameters":[{"name":"Accent21-1","volume":90,"pitch":100,"pan":0}]},{"code":224,"indent":0,"parameters":[[255,255,255,170],60,false]},{"code":356,"indent":0,"parameters":["NameBoxSet Кейджи"]},{"code":101,"indent":0,"parameters":["",0,0,2]},{"code":401,"indent":0,"parameters":["\"...Всё в порядке. Ты ничего не забыла.\""]},{"code":356,"indent":0,"parameters":["MSGSE TALK CLEAR"]},{"code":356,"indent":0,"parameters":["NameBoxReset"]},{"code":101,"indent":0,"parameters":["",0,1,2]},{"code":401,"indent":0,"parameters":["Правда?.."]},{"code":356,"indent":0,"parameters":["MSGSE TALK DEFAULT"]},{"code":231,"indent":0,"parameters":[31,"cara4-9",1,0,408,312,100,100,255,0]},{"code":356,"indent":0,"parameters":["NameBoxSet Кью-таро"]},{"code":101,"indent":0,"parameters":["",0,0,2]},{"code":401,"indent":0,"parameters":["\"...Ты прост устала. Отдохни.\""]},{"code":356,"indent":0,"parameters":["MSGSE TALK CLEAR"]},{"code":356,"indent":0,"parameters":["NameBoxReset"]},{"code":101,"indent":0,"parameters":["",0,1,2]},{"code":401,"indent":0,"parameters":["Нет, мой разум кажется совершенно чистым..."]},{"code":356,"indent":0,"parameters":["MSGSE TALK DEFAULT"]},{"code":111,"indent":0,"parameters":[0,642,0]},{"code":231,"indent":1,"parameters":[31,"cara6-4",1,0,408,312,100,100,255,0]},{"code":356,"indent":1,"parameters":["NameBoxSet Реко"]},{"code":101,"indent":1,"parameters":["",0,0,2]},{"code":401,"indent":1,"parameters":["\"T... Tогда волноваться не о чем, да?\""]},{"code":0,"indent":1,"parameters":[]},{"code":411,"indent":0,"parameters":[]},{"code":231,"indent":1,"parameters":[31,"cara11-4",1,0,408,312,100,100,255,0]},{"code":356,"indent":1,"parameters":["NameBoxSet Элис"]},{"code":101,"indent":1,"parameters":["",0,0,2]},{"code":401,"indent":1,"parameters":["\"...Хмпф. Значит, не о чем волноваться?\""]},{"code":0,"indent":1,"parameters":[]},{"code":412,"indent":0,"parameters":[]},{"code":356,"indent":0,"parameters":["MSGSE TALK CLEAR"]},{"code":356,"indent":0,"parameters":["NameBoxReset"]},{"code":101,"indent":0,"parameters":["",0,1,2]},{"code":401,"indent":0,"parameters":["Но..."]},{"code":356,"indent":0,"parameters":["MSGSE TALK DEFAULT"]},{"code":231,"indent":0,"parameters":[31,"cara9-4",1,0,408,312,100,100,255,0]},{"code":356,"indent":0,"parameters":["NameBoxSet Гин"]},{"code":101,"indent":0,"parameters":["",0,0,2]},{"code":401,"indent":0,"parameters":["\"..........\""]},{"code":232,"indent":0,"parameters":[31,0,1,0,408,312,100,100,0,0,30,true]},{"code":356,"indent":0,"parameters":["MSGSE TALK CLEAR"]},{"code":356,"indent":0,"parameters":["NameBoxReset"]},{"code":101,"indent":0,"parameters":["",0,1,2]},{"code":401,"indent":0,"parameters":["Я должна... всё вспомнить..."]},{"code":101,"indent":0,"parameters":["",0,1,2]},{"code":401,"indent":0,"parameters":["\\.Нао... и Канной..."]},{"code":401,"indent":0,"parameters":["Пришлось пожертвовать..."]},{"code":231,"indent":0,"parameters":[31,"cara1-11",1,0,408,312,100,100,0,0]},{"code":234,"indent":0,"parameters":[31,[255,255,255,0],1,true]},{"code":232,"indent":0,"parameters":[31,0,1,0,408,312,100,100,255,0,30,true]},{"code":101,"indent":0,"parameters":["",0,1,2]},{"code":401,"indent":0,"parameters":["\\.О чём я забыла?.."]},{"code":356,"indent":0,"parameters":["MSGSE TALK DEFAULT"]},{"code":232,"indent":0,"parameters":[31,0,1,0,408,312,100,100,0,0,30,true]},{"code":231,"indent":0,"parameters":[31,"cara2-1",1,0,408,312,100,100,0,0]},{"code":232,"indent":0,"parameters":[31,0,1,0,408,312,100,100,255,0,30,true]},{"code":250,"indent":0,"parameters":[{"name":"Accent28-1","volume":90,"pitch":100,"pan":0}]},{"code":224,"indent":0,"parameters":[[255,255,255,170],60,false]},{"code":356,"indent":0,"parameters":["NameBoxSet Кейджи"]},{"code":101,"indent":0,"parameters":["",0,0,2]},{"code":401,"indent":0,"parameters":["\"Тогда не стоит просто сидеть "]},{"code":401,"indent":0,"parameters":[" и тратить время на размышления.\""]},{"code":231,"indent":0,"parameters":[31,"cara2-7",1,0,408,312,100,100,255,0]},{"code":356,"indent":0,"parameters":["NameBoxSet Кейджи"]},{"code":101,"indent":0,"parameters":["",0,0,2]},{"code":401,"indent":0,"parameters":["\\.\"Надо шевелиться. ...Чтобы больше никто не погиб.\""]},{"code":356,"indent":0,"parameters":["MSGSE TALK CLEAR"]},{"code":356,"indent":0,"parameters":["NameBoxReset"]},{"code":101,"indent":0,"parameters":["",0,1,2]},{"code":401,"indent":0,"parameters":["...Точно."]},{"code":356,"indent":0,"parameters":["MSGSE TALK DEFAULT"]},{"code":232,"indent":0,"parameters":[31,0,1,0,408,312,100,100,0,0,60,true]},{"code":235,"indent":0,"parameters":[31]},{"code":230,"indent":0,"parameters":[90]},{"code":250,"indent":0,"parameters":[{"name":"sceneswitch2","volume":100,"pitch":80,"pan":0}]},{"code":231,"indent":0,"parameters":[52,"title",1,0,408,294,100,100,0,0]},{"code":232,"indent":0,"parameters":[52,0,1,0,408,294,100,100,255,0,30,true]},{"code":230,"indent":0,"parameters":[130]},{"code":232,"indent":0,"parameters":[52,0,1,0,408,294,100,100,0,0,30,true]},{"code":235,"indent":0,"parameters":[52]},{"code":230,"indent":0,"parameters":[60]},{"code":356,"indent":0,"parameters":["NameBoxReset"]},{"code":221,"indent":0,"parameters":[]},{"code":201,"indent":0,"parameters":[0,184,0,0,0,0]},{"code":231,"indent":0,"parameters":[14,"menu",1,0,106,572,100,100,255,0]},{"code":356,"indent":0,"parameters":["P_CALL_CE 14 8 1 ON"]},{"code":230,"indent":0,"parameters":[90]},{"code":222,"indent":0,"parameters":[]},{"code":230,"indent":0,"parameters":[30]},{"code":231,"indent":0,"parameters":[31,"cara15-1",1,0,408,312,100,100,0,0]},{"code":232,"indent":0,"parameters":[31,0,1,0,408,312,100,100,255,0,60,true]},{"code":250,"indent":0,"parameters":[{"name":"Accent21-1","volume":90,"pitch":100,"pan":0}]},{"code":224,"indent":0,"parameters":[[255,255,255,170],60,false]},{"code":356,"indent":0,"parameters":["NameBoxSet Сафалин"]},{"code":101,"indent":0,"parameters":["",0,0,2]},{"code":401,"indent":0,"parameters":["\"Внимание... Скоро этаж будет закрыт.\""]},{"code":231,"indent":0,"parameters":[31,"cara15-2",1,0,408,312,100,100,255,0]},{"code":101,"indent":0,"parameters":["",0,0,2]},{"code":401,"indent":0,"parameters":["\\.\"Если вы не перейдёте на следующий этаж"]},{"code":401,"indent":0,"parameters":[" в течение пяти минут, ваши ошейники активируются...\""]},{"code":356,"indent":0,"parameters":["NameBoxSet Сара"]},{"code":101,"indent":0,"parameters":["",0,0,2]},{"code":401,"indent":0,"parameters":["\\.\"...Понятно.\""]},{"code":356,"indent":0,"parameters":["NameBoxSet Сафалин"]},{"code":231,"indent":0,"parameters":[31,"cara15-8",1,0,408,312,100,100,255,0]},{"code":101,"indent":0,"parameters":["",0,0,2]},{"code":401,"indent":0,"parameters":["\\.\"Прошу прощения...\""]},{"code":232,"indent":0,"parameters":[31,0,1,0,408,312,100,100,0,0,60,true]},{"code":231,"indent":0,"parameters":[31,"cara4-6",1,0,408,312,100,100,0,0]},{"code":232,"indent":0,"parameters":[31,0,1,0,408,312,100,100,255,0,30,true]},{"code":250,"indent":0,"parameters":[{"name":"feed1","volume":90,"pitch":100,"pan":0}]},{"code":225,"indent":0,"parameters":[7,7,30,false]},{"code":356,"indent":0,"parameters":["NameBoxSet Кью-таро"]},{"code":101,"indent":0,"parameters":["",0,0,2]},{"code":401,"indent":0,"parameters":["\"Эт плохо!.."]},{"code":401,"indent":0,"parameters":[" Надо валить отсюда побыстрее, э?\""]},{"code":111,"indent":0,"parameters":[0,642,0]},{"code":231,"indent":1,"parameters":[31,"cara6-10",1,0,408,312,100,100,255,0]},{"code":250,"indent":1,"parameters":[{"name":"se_maoudamashii_magical14","volume":100,"pitch":100,"pan":0}]},{"code":224,"indent":1,"parameters":[[255,255,255,170],60,false]},{"code":356,"indent":1,"parameters":["NameBoxSet Реко"]},{"code":101,"indent":1,"parameters":["",0,0,2]},{"code":401,"indent":1,"parameters":["\\.\"Послушайте..."]},{"code":401,"indent":1,"parameters":[" Нельзя оставить тут этого придурка Соу.\""]},{"code":231,"indent":1,"parameters":[31,"cara9-3",1,0,408,312,100,100,255,0]},{"code":356,"indent":1,"parameters":["NameBoxSet Гин"]},{"code":101,"indent":1,"parameters":["",0,0,2]},{"code":401,"indent":1,"parameters":["\\.\"Наверное, стоит его подождать, мяу...\""]},{"code":231,"indent":1,"parameters":[31,"cara2-6",1,0,408,312,100,100,255,0]},{"code":356,"indent":1,"parameters":["NameBoxSet Кейджи"]},{"code":101,"indent":1,"parameters":["",0,0,2]},{"code":401,"indent":1,"parameters":["\\.\"Если он до сих пор не появился..."]},{"code":401,"indent":1,"parameters":[" То мог пойти вперёд.\""]},{"code":0,"indent":1,"parameters":[]},{"code":411,"indent":0,"parameters":[]},{"code":231,"indent":1,"parameters":[31,"cara11-14",1,0,408,312,100,100,255,0]},{"code":250,"indent":1,"parameters":[{"name":"se_maoudamashii_magical14","volume":100,"pitch":100,"pan":0}]},{"code":224,"indent":1,"parameters":[[255,255,255,170],60,false]},{"code":356,"indent":1,"parameters":["NameBoxSet Элис"]},{"code":101,"indent":1,"parameters":["",0,0,2]},{"code":401,"indent":1,"parameters":["\\.\"Хмпф... Нет необходимости ждать его.\""]},{"code":231,"indent":1,"parameters":[31,"cara9-3",1,0,408,312,100,100,255,0]},{"code":356,"indent":1,"parameters":["NameBoxSet Гин"]},{"code":101,"indent":1,"parameters":["",0,0,2]},{"code":401,"indent":1,"parameters":["\\.\"Мяу... Но если мы его оставим, он умрёт...\""]},{"code":231,"indent":1,"parameters":[31,"cara11-4",1,0,408,312,100,100,255,0]},{"code":356,"indent":1,"parameters":["NameBoxSet Элис"]},{"code":101,"indent":1,"parameters":["",0,0,2]},{"code":401,"indent":1,"parameters":["\\.\"Я так не думаю..."]},{"code":401,"indent":1,"parameters":[" Не думаете, что он мог отправиться вперёд?\""]},{"code":0,"indent":1,"parameters":[]},{"code":412,"indent":0,"parameters":[]},{"code":356,"indent":0,"parameters":["NameBoxSet Сара"]},{"code":101,"indent":0,"parameters":["",0,0,2]},{"code":401,"indent":0,"parameters":["\\.\\C[4](Интересно, куда он делся...)"]},{"code":250,"indent":0,"parameters":[{"name":"Accent21-1","volume":90,"pitch":100,"pan":0}]},{"code":224,"indent":0,"parameters":[[255,255,255,170],60,false]},{"code":356,"indent":0,"parameters":["NameBoxSet Сара"]},{"code":101,"indent":0,"parameters":["",0,0,2]},{"code":401,"indent":0,"parameters":["\\.\\C[4](Может... он больше не хочет нас видеть.)"]},{"code":231,"indent":0,"parameters":[31,"cara9-6",1,0,408,312,100,100,255,0]},{"code":250,"indent":0,"parameters":[{"name":"Accent28-1","volume":90,"pitch":100,"pan":0}]},{"code":224,"indent":0,"parameters":[[255,255,255,170],60,false]},{"code":356,"indent":0,"parameters":["NameBoxSet Гин"]},{"code":101,"indent":0,"parameters":["",0,0,2]},{"code":401,"indent":0,"parameters":["\\.\"П-понял, вуф! Я поищу его, мяу!"]},{"code":401,"indent":0,"parameters":[" Ждите здесь, вуф!\""]},{"code":111,"indent":0,"parameters":[0,642,0]},{"code":231,"indent":1,"parameters":[31,"cara6-10",1,0,408,312,100,100,255,0]},{"code":250,"indent":1,"parameters":[{"name":"feed1","volume":90,"pitch":100,"pan":0}]},{"code":225,"indent":1,"parameters":[7,7,30,false]},{"code":356,"indent":1,"parameters":["NameBoxSet Реко"]},{"code":101,"indent":1,"parameters":["",0,0,2]},{"code":401,"indent":1,"parameters":["\\.\"Нет, Гин! Ладно, я...\""]},{"code":0,"indent":1,"parameters":[]},{"code":411,"indent":0,"parameters":[]},{"code":231,"indent":1,"parameters":[31,"cara11-7",1,0,408,312,100,100,255,0]},{"code":250,"indent":1,"parameters":[{"name":"feed1","volume":90,"pitch":100,"pan":0}]},{"code":225,"indent":1,"parameters":[7,7,30,false]},{"code":356,"indent":1,"parameters":["NameBoxSet Элис"]},{"code":101,"indent":1,"parameters":["",0,0,2]},{"code":401,"indent":1,"parameters":["\\.\"Прекрати!"]},{"code":401,"indent":1,"parameters":[" Выходит так, что мы эгоисты!\""]},{"code":0,"indent":1,"parameters":[]},{"code":412,"indent":0,"parameters":[]},{"code":232,"indent":0,"parameters":[31,0,1,0,408,312,100,100,0,0,30,true]},{"code":250,"indent":0,"parameters":[{"name":"se_maoudamashii_magical14","volume":90,"pitch":100,"pan":0}]},{"code":224,"indent":0,"parameters":[[255,255,255,170],60,false]},{"code":356,"indent":0,"parameters":["NameBoxSet Голос"]},{"code":101,"indent":0,"parameters":["",0,0,1]},{"code":401,"indent":0,"parameters":["\"Как шумно...\""]},{"code":231,"indent":0,"parameters":[31,"cara5-2",1,0,408,312,100,100,0,0]},{"code":232,"indent":0,"parameters":[31,0,1,0,408,312,100,100,255,0,30,true]},{"code":250,"indent":0,"parameters":[{"name":"Accent28-1","volume":90,"pitch":100,"pan":0}]},{"code":224,"indent":0,"parameters":[[255,255,255,170],60,false]},{"code":356,"indent":0,"parameters":["NameBoxSet Соу"]},{"code":101,"indent":0,"parameters":["",0,0,2]},{"code":401,"indent":0,"parameters":["\"Что с вами такое, ребята?\""]},{"code":241,"indent":0,"parameters":[{"name":"kakure1","volume":70,"pitch":100,"pan":0}]},{"code":231,"indent":0,"parameters":[31,"cara2-2",1,0,408,312,100,100,255,0]},{"code":356,"indent":0,"parameters":["NameBoxSet Кейджи"]},{"code":101,"indent":0,"parameters":["",0,0,2]},{"code":401,"indent":0,"parameters":["\\.\"Соу...\""]},{"code":111,"indent":0,"parameters":[0,642,0]},{"code":231,"indent":1,"parameters":[31,"cara6-8",1,0,408,312,100,100,255,0]},{"code":356,"indent":1,"parameters":["NameBoxSet Реко"]},{"code":101,"indent":1,"parameters":["",0,0,2]},{"code":401,"indent":1,"parameters":["\\.\"...Как раз вовремя, ха.\""]},{"code":0,"indent":1,"parameters":[]},{"code":411,"indent":0,"parameters":[]},{"code":231,"indent":1,"parameters":[31,"cara11-18",1,0,408,312,100,100,255,0]},{"code":356,"indent":1,"parameters":["NameBoxSet Элис"]},{"code":101,"indent":1,"parameters":["",0,0,2]},{"code":401,"indent":1,"parameters":["\\.\"...Удивительная пунктуальность, ха?\""]},{"code":0,"indent":1,"parameters":[]},{"code":412,"indent":0,"parameters":[]},{"code":231,"indent":0,"parameters":[31,"cara5-3",1,0,408,312,100,100,255,0]},{"code":356,"indent":0,"parameters":["NameBoxSet Соу"]},{"code":101,"indent":0,"parameters":["",0,0,2]},{"code":401,"indent":0,"parameters":["\\.\"Ахаха. Попробуйте в следующий раз поприветствовать"]},{"code":401,"indent":0,"parameters":[" меня с улыбкой. Мы же союзники, ведь так?\""]},{"code":231,"indent":0,"parameters":[31,"cara4-7",1,0,408,312,100,100,255,0]},{"code":250,"indent":0,"parameters":[{"name":"se_maoudamashii_magical14","volume":90,"pitch":100,"pan":0}]},{"code":224,"indent":0,"parameters":[[255,255,255,170],60,false]},{"code":356,"indent":0,"parameters":["NameBoxSet Кью-таро"]},{"code":101,"indent":0,"parameters":["",0,0,2]},{"code":401,"indent":0,"parameters":["\\.\"Как будто кто-то щас может улыбаться...\""]},{"code":231,"indent":0,"parameters":[31,"cara5-2",1,0,408,312,100,100,255,0]},{"code":250,"indent":0,"parameters":[{"name":"Onmtp-Surprise03-1","volume":90,"pitch":90,"pan":0}]},{"code":224,"indent":0,"parameters":[[255,255,255,170],60,false]},{"code":356,"indent":0,"parameters":["NameBoxSet Соу"]},{"code":101,"indent":0,"parameters":["",0,0,2]},{"code":401,"indent":0,"parameters":["\\.\"Хах? Но я улыбаюсь. Видите?\""]},{"code":231,"indent":0,"parameters":[31,"cara4-6",1,0,408,312,100,100,255,0]},{"code":250,"indent":0,"parameters":[{"name":"Damage4","volume":90,"pitch":100,"pan":0}]},{"code":225,"indent":0,"parameters":[7,7,30,false]},{"code":356,"indent":0,"parameters":["NameBoxSet Кью-таро"]},{"code":101,"indent":0,"parameters":["",0,0,2]},{"code":401,"indent":0,"parameters":["\\.\"Заканчивай уже!"]},{"code":401,"indent":0,"parameters":[" Ты пытался её защитить... А мы!..\""]},{"code":231,"indent":0,"parameters":[31,"cara5-16",1,0,408,312,100,100,255,0]},{"code":356,"indent":0,"parameters":["NameBoxSet Соу"]},{"code":101,"indent":0,"parameters":["",0,0,2]},{"code":401,"indent":0,"parameters":["\\.\"О чём ты говоришь?..\""]},{"code":111,"indent":0,"parameters":[0,642,0]},{"code":231,"indent":1,"parameters":[31,"cara6-10",1,0,408,312,100,100,255,0]},{"code":250,"indent":1,"parameters":[{"name":"feed1","volume":90,"pitch":100,"pan":0}]},{"code":225,"indent":1,"parameters":[7,7,30,false]},{"code":356,"indent":1,"parameters":["NameBoxSet Реко"]},{"code":101,"indent":1,"parameters":["",0,0,2]},{"code":401,"indent":1,"parameters":["\\.\"О... о чём он говорит?!..\""]},{"code":0,"indent":1,"parameters":[]},{"code":411,"indent":0,"parameters":[]},{"code":231,"indent":1,"parameters":[31,"cara4-6",1,0,408,312,100,100,255,0]},{"code":250,"indent":1,"parameters":[{"name":"feed1","volume":90,"pitch":100,"pan":0}]},{"code":225,"indent":1,"parameters":[7,7,30,false]},{"code":356,"indent":1,"parameters":["NameBoxSet Кью-таро"]},{"code":101,"indent":1,"parameters":["",0,0,2]},{"code":401,"indent":1,"parameters":["\\.\"О... о чём я говорю?!..\""]},{"code":0,"indent":1,"parameters":[]},{"code":412,"indent":0,"parameters":[]},{"code":231,"indent":0,"parameters":[31,"cara5-19",1,0,408,312,100,100,255,0]},{"code":250,"indent":0,"parameters":[{"name":"Accent21-1","volume":90,"pitch":100,"pan":0}]},{"code":224,"indent":0,"parameters":[[255,255,255,170],60,false]},{"code":356,"indent":0,"parameters":["NameBoxSet Соу"]},{"code":101,"indent":0,"parameters":["",0,0,2]},{"code":401,"indent":0,"parameters":["\\.\"Охх, ты про Канну?..\""]},{"code":231,"indent":0,"parameters":[31,"cara5-15",1,0,408,312,100,100,255,0]},{"code":101,"indent":0,"parameters":["",0,0,2]},{"code":401,"indent":0,"parameters":["\\.\"Да, обидно. В Главной Игре"]},{"code":401,"indent":0,"parameters":[" Kанна даже пыталась получить \\C[10]Жертву\\C[0]...\""]},{"code":231,"indent":0,"parameters":[31,"cara5-18",1,0,408,312,100,100,255,0]},{"code":101,"indent":0,"parameters":["",0,0,2]},{"code":401,"indent":0,"parameters":["\\.\"Но увы, у неё не было шанса выбрать меня,"]},{"code":401,"indent":0,"parameters":[" и мы не сбежали вместе.\""]},{"code":231,"indent":0,"parameters":[31,"cara5-2",1,0,408,312,100,100,255,0]},{"code":242,"indent":0,"parameters":[1]},{"code":250,"indent":0,"parameters":[{"name":"horror_piano chord3","volume":90,"pitch":100,"pan":0}]},{"code":224,"indent":0,"parameters":[[255,0,0,170],60,false]},{"code":101,"indent":0,"parameters":["",0,0,2]},{"code":401,"indent":0,"parameters":["\\.\\C[10]\"Всё-таки не смог ею воспользоваться... Досадно.\""]},{"code":231,"indent":0,"parameters":[31,"cara9-4",1,0,408,312,100,100,255,0]},{"code":356,"indent":0,"parameters":["NameBoxSet Гин"]},{"code":101,"indent":0,"parameters":["",0,0,2]},{"code":401,"indent":0,"parameters":["\\.\"..........\""]},{"code":231,"indent":0,"parameters":[31,"cara2-1",1,0,408,312,100,100,255,0]},{"code":250,"indent":0,"parameters":[{"name":"sceneswitch2","volume":90,"pitch":100,"pan":0}]},{"code":224,"indent":0,"parameters":[[255,255,255,170],60,false]},{"code":356,"indent":0,"parameters":["NameBoxSet Кейджи"]},{"code":101,"indent":0,"parameters":["",0,0,2]},{"code":401,"indent":0,"parameters":["\\.\"Вахаха...\""]},{"code":231,"indent":0,"parameters":[31,"cara5-17",1,0,408,312,100,100,255,0]},{"code":356,"indent":0,"parameters":["NameBoxSet Соу"]},{"code":101,"indent":0,"parameters":["",0,0,2]},{"code":401,"indent":0,"parameters":["\\.\"Что смешного?\""]},{"code":231,"indent":0,"parameters":[31,"cara2-2",1,0,408,312,100,100,255,0]},{"code":356,"indent":0,"parameters":["NameBoxSet Кейджи"]},{"code":101,"indent":0,"parameters":["",0,0,2]},{"code":401,"indent":0,"parameters":["\\.\"Ах, мне даже тебя жаль..."]},{"code":401,"indent":0,"parameters":[" Если бы такое и произошло...\""]},{"code":231,"indent":0,"parameters":[31,"cara2-1",1,0,408,312,100,100,255,0]},{"code":250,"indent":0,"parameters":[{"name":"se_maoudamashii_magical14","volume":90,"pitch":100,"pan":0}]},{"code":224,"indent":0,"parameters":[[255,255,255,170],60,false]},{"code":101,"indent":0,"parameters":["",0,0,2]},{"code":401,"indent":0,"parameters":["\\.\"Kанна выбрала бы Сару, а не тебя.\""]},{"code":231,"indent":0,"parameters":[31,"cara5-5",1,0,408,312,100,100,255,0]},{"code":250,"indent":0,"parameters":[{"name":"feed1","volume":90,"pitch":100,"pan":0}]},{"code":225,"indent":0,"parameters":[7,7,30,false]},{"code":356,"indent":0,"parameters":["NameBoxSet Соу"]},{"code":101,"indent":0,"parameters":["",0,0,2]},{"code":401,"indent":0,"parameters":["\\.\"!..\""]},{"code":241,"indent":0,"parameters":[{"name":"sinzizitu","volume":80,"pitch":100,"pan":0}]},{"code":231,"indent":0,"parameters":[31,"cara2-1",1,0,408,312,100,100,255,0]},{"code":356,"indent":0,"parameters":["NameBoxSet Кейджи"]},{"code":101,"indent":0,"parameters":["",0,0,2]},{"code":401,"indent":0,"parameters":["\\.\"Хаха... Ты правда думал, что она бы выбрала тебя?\""]},{"code":231,"indent":0,"parameters":[31,"cara5-32",1,0,408,312,100,100,255,0]},{"code":250,"indent":0,"parameters":[{"name":"Damage4","volume":90,"pitch":100,"pan":0}]},{"code":225,"indent":0,"parameters":[7,7,30,false]},{"code":356,"indent":0,"parameters":["NameBoxSet Соу"]},{"code":101,"indent":0,"parameters":["",0,0,2]},{"code":401,"indent":0,"parameters":["\\.\"Заткнись, Кейджи!..\""]},{"code":231,"indent":0,"parameters":[31,"cara5-30",1,0,408,312,100,100,255,0]},{"code":250,"indent":0,"parameters":[{"name":"feed1","volume":90,"pitch":100,"pan":0}]},{"code":225,"indent":0,"parameters":[7,7,30,false]},{"code":101,"indent":0,"parameters":["",0,0,2]},{"code":401,"indent":0,"parameters":["\\.\"Я это знаю!.. Конечно я это знаю!\""]},{"code":231,"indent":0,"parameters":[31,"cara5-32",1,0,408,312,100,100,255,0]},{"code":250,"indent":0,"parameters":[{"name":"feed1","volume":90,"pitch":100,"pan":0}]},{"code":225,"indent":0,"parameters":[7,7,30,false]},{"code":101,"indent":0,"parameters":["",0,0,2]},{"code":401,"indent":0,"parameters":["\\.\"Вы просто смеётесь надо мной, потому что мне "]},{"code":401,"indent":0,"parameters":[" суждено умереть! Ну так смейтесь...\""]},{"code":231,"indent":0,"parameters":[31,"cara2-3",1,0,408,312,100,100,255,0]},{"code":241,"indent":0,"parameters":[{"name":"","volume":90,"pitch":100,"pan":0}]},{"code":250,"indent":0,"parameters":[{"name":"Accent28-1","volume":90,"pitch":100,"pan":0}]},{"code":224,"indent":0,"parameters":[[255,255,255,170],60,false]},{"code":356,"indent":0,"parameters":["NameBoxSet Кейджи"]},{"code":101,"indent":0,"parameters":["",0,0,2]},{"code":401,"indent":0,"parameters":["\\.\"Хватит лгать, Соу.\""]},{"code":231,"indent":0,"parameters":[31,"cara5-34",1,0,408,312,100,100,255,0]},{"code":356,"indent":0,"parameters":["NameBoxSet Соу"]},{"code":101,"indent":0,"parameters":["",0,0,2]},{"code":401,"indent":0,"parameters":["\\.\"..........\""]},{"code":231,"indent":0,"parameters":[31,"cara2-4",1,0,408,312,100,100,255,0]},{"code":356,"indent":0,"parameters":["NameBoxSet Кейджи"]},{"code":101,"indent":0,"parameters":["",0,0,2]},{"code":401,"indent":0,"parameters":["\\.\"Ты рисковал жизнью, чтобы защитить Канну."]},{"code":401,"indent":0,"parameters":[" Ты был готов пожертвовать собой...\""]},{"code":231,"indent":0,"parameters":[31,"cara2-3",1,0,408,312,100,100,255,0]},{"code":250,"indent":0,"parameters":[{"name":"Accent21-1","volume":90,"pitch":100,"pan":0}]},{"code":224,"indent":0,"parameters":[[255,255,255,170],60,false]},{"code":101,"indent":0,"parameters":["",0,0,2]},{"code":401,"indent":0,"parameters":["\\.\"Это неразумные действия."]},{"code":401,"indent":0,"parameters":[" Здесь за тебя решило твоё сердце.\""]},{"code":231,"indent":0,"parameters":[31,"cara5-34",1,0,408,312,100,100,255,0]},{"code":356,"indent":0,"parameters":["NameBoxSet Соу"]},{"code":101,"indent":0,"parameters":["",0,0,2]},{"code":401,"indent":0,"parameters":["\\.\"..........\""]},{"code":231,"indent":0,"parameters":[31,"cara2-16",1,0,408,312,100,100,255,0]},{"code":250,"indent":0,"parameters":[{"name":"sceneswitch2","volume":90,"pitch":100,"pan":0}]},{"code":224,"indent":0,"parameters":[[255,255,255,170],60,false]},{"code":356,"indent":0,"parameters":["NameBoxSet Кейджи"]},{"code":101,"indent":0,"parameters":["",0,0,2]},{"code":401,"indent":0,"parameters":["\\.\"А мы тебе помешали.\""]},{"code":231,"indent":0,"parameters":[31,"cara9-13",1,0,408,312,100,100,255,0]},{"code":356,"indent":0,"parameters":["NameBoxSet Гин"]},{"code":101,"indent":0,"parameters":["",0,0,2]},{"code":401,"indent":0,"parameters":["\\.\"Шмыг...\""]},{"code":231,"indent":0,"parameters":[31,"cara2-3",1,0,408,312,100,100,255,0]},{"code":250,"indent":0,"parameters":[{"name":"Accent21-1","volume":90,"pitch":100,"pan":0}]},{"code":224,"indent":0,"parameters":[[255,255,255,170],60,false]},{"code":356,"indent":0,"parameters":["NameBoxSet Кейджи"]},{"code":101,"indent":0,"parameters":["",0,0,2]},{"code":401,"indent":0,"parameters":["\\.\"...Ты наверняка ненавидишь нас до смерти.\""]},{"code":231,"indent":0,"parameters":[31,"cara2-4",1,0,408,312,100,100,255,0]},{"code":101,"indent":0,"parameters":["",0,0,2]},{"code":401,"indent":0,"parameters":["\\.\"Но несмотря на это... Нам нужно сотрудничать.\""]},{"code":231,"indent":0,"parameters":[31,"cara2-3",1,0,408,312,100,100,255,0]},{"code":101,"indent":0,"parameters":["",0,0,2]},{"code":401,"indent":0,"parameters":["\\.\"Канна... сделала свой выбор...\""]},{"code":231,"indent":0,"parameters":[31,"cara5-18",1,0,408,312,100,100,255,0]},{"code":250,"indent":0,"parameters":[{"name":"sceneswitch2","volume":90,"pitch":100,"pan":0}]},{"code":224,"indent":0,"parameters":[[255,255,255,170],60,false]},{"code":356,"indent":0,"parameters":["NameBoxSet Соу"]},{"code":101,"indent":0,"parameters":["",0,0,2]},{"code":401,"indent":0,"parameters":["\\.\"...Это ни к чему не приведёт.\""]},{"code":231,"indent":0,"parameters":[31,"cara5-19",1,0,408,312,100,100,255,0]},{"code":101,"indent":0,"parameters":["",0,0,2]},{"code":401,"indent":0,"parameters":["\\.\"Хватит. Идём на следующий этаж.\""]},{"code":231,"indent":0,"parameters":[31,"cara2-3",1,0,408,312,100,100,255,0]},{"code":356,"indent":0,"parameters":["NameBoxSet Кейджи"]},{"code":101,"indent":0,"parameters":["",0,0,2]},{"code":401,"indent":0,"parameters":["\\.\"Соу...\""]},{"code":231,"indent":0,"parameters":[31,"cara5-19",1,0,408,312,100,100,255,0]},{"code":356,"indent":0,"parameters":["NameBoxSet Соу"]},{"code":101,"indent":0,"parameters":["",0,0,2]},{"code":401,"indent":0,"parameters":["\\.\"Ты странный, Кейджи.\""]},{"code":231,"indent":0,"parameters":[31,"cara5-18",1,0,408,312,100,100,255,0]},{"code":101,"indent":0,"parameters":["",0,0,2]},{"code":401,"indent":0,"parameters":["\\.\"Во время дискуссии, клянусь, ты желал мне смерти.\""]},{"code":231,"indent":0,"parameters":[31,"cara2-3",1,0,408,312,100,100,255,0]},{"code":250,"indent":0,"parameters":[{"name":"Accent21-1","volume":90,"pitch":100,"pan":0}]},{"code":224,"indent":0,"parameters":[[255,255,255,170],60,false]},{"code":356,"indent":0,"parameters":["NameBoxSet Кейджи"]},{"code":101,"indent":0,"parameters":["",0,0,2]},{"code":401,"indent":0,"parameters":["\\.\"Что ж... теперь всё по-другому.\""]},{"code":231,"indent":0,"parameters":[31,"cara5-15",1,0,408,312,100,100,255,0]},{"code":356,"indent":0,"parameters":["NameBoxSet Соу"]},{"code":101,"indent":0,"parameters":["",0,0,2]},{"code":401,"indent":0,"parameters":["\\.\"..........\""]},{"code":250,"indent":0,"parameters":[{"name":"asioto2","volume":90,"pitch":100,"pan":0}]},{"code":232,"indent":0,"parameters":[31,0,1,0,408,312,100,100,0,0,60,true]},{"code":235,"indent":0,"parameters":[31]},{"code":230,"indent":0,"parameters":[30]},{"code":251,"indent":0,"parameters":[]},{"code":111,"indent":0,"parameters":[0,642,0]},{"code":231,"indent":1,"parameters":[31,"cara6-6",1,0,408,312,100,100,0,0]},{"code":232,"indent":1,"parameters":[31,0,1,0,408,312,100,100,255,0,30,true]},{"code":356,"indent":1,"parameters":["NameBoxSet Реко"]},{"code":101,"indent":1,"parameters":["",0,0,2]},{"code":401,"indent":1,"parameters":["\"Идёмте уже. Разберёмся с этим позже.\""]},{"code":231,"indent":1,"parameters":[31,"cara9-3",1,0,408,312,100,100,255,0]},{"code":356,"indent":1,"parameters":["NameBoxSet Гин"]},{"code":101,"indent":1,"parameters":["",0,0,2]},{"code":401,"indent":1,"parameters":["\\.\"Mяу...\""]},{"code":231,"indent":1,"parameters":[31,"cara6-8",1,0,408,312,100,100,255,0]},{"code":250,"indent":1,"parameters":[{"name":"se_maoudamashii_magical14","volume":90,"pitch":100,"pan":0}]},{"code":224,"indent":1,"parameters":[[255,255,255,170],60,false]},{"code":356,"indent":1,"parameters":["NameBoxSet Реко"]},{"code":101,"indent":1,"parameters":["",0,0,2]},{"code":401,"indent":1,"parameters":["\\.\"Знаю, Гин."]},{"code":401,"indent":1,"parameters":[" Я бы тоже хотела что-то с этим сделать.\""]},{"code":231,"indent":1,"parameters":[31,"cara6-9",1,0,408,312,100,100,255,0]},{"code":250,"indent":1,"parameters":[{"name":"feed1","volume":90,"pitch":100,"pan":0}]},{"code":225,"indent":1,"parameters":[7,7,30,false]},{"code":101,"indent":1,"parameters":["",0,0,2]},{"code":401,"indent":1,"parameters":["\\.\"Потому что теперь я знаю, что даже"]},{"code":401,"indent":1,"parameters":[" у Соу есть сердце... ...Твою ж мать.\""]},{"code":0,"indent":1,"parameters":[]},{"code":411,"indent":0,"parameters":[]},{"code":231,"indent":1,"parameters":[31,"cara11-18",1,0,408,312,100,100,0,0]},{"code":232,"indent":1,"parameters":[31,0,1,0,408,312,100,100,255,0,30,true]},{"code":250,"indent":1,"parameters":[{"name":"se_maoudamashii_magical14","volume":90,"pitch":100,"pan":0}]},{"code":224,"indent":1,"parameters":[[255,255,255,170],60,false]},{"code":356,"indent":1,"parameters":["NameBoxSet Элис"]},{"code":101,"indent":1,"parameters":["",0,0,2]},{"code":401,"indent":1,"parameters":["\"...Я не понимаю его. Этот Соу...\""]},{"code":231,"indent":1,"parameters":[31,"cara9-4",1,0,408,312,100,100,255,0]},{"code":356,"indent":1,"parameters":["NameBoxSet Гин"]},{"code":101,"indent":1,"parameters":["",0,0,2]},{"code":401,"indent":1,"parameters":["\\.\"Он просто в отчаянии, мяу... Я уверен...\""]},{"code":231,"indent":1,"parameters":[31,"cara11-4",1,0,408,312,100,100,255,0]},{"code":356,"indent":1,"parameters":["NameBoxSet Элис"]},{"code":101,"indent":1,"parameters":["",0,0,2]},{"code":401,"indent":1,"parameters":["\\.\"...Хмпф.\""]},{"code":231,"indent":1,"parameters":[31,"cara11-1",1,0,408,312,100,100,255,0]},{"code":101,"indent":1,"parameters":["",0,0,2]},{"code":401,"indent":1,"parameters":["\\.\"Ну что ж, я полагаю, мы все в отчаянии..."]},{"code":401,"indent":1,"parameters":[" Вперёд, на третий этаж, пока мы ещё живы.\""]},{"code":0,"indent":1,"parameters":[]},{"code":412,"indent":0,"parameters":[]},{"code":232,"indent":0,"parameters":[31,0,1,0,408,312,100,100,0,0,30,true]},{"code":235,"indent":0,"parameters":[31]},{"code":117,"indent":0,"parameters":[13]},{"code":241,"indent":0,"parameters":[{"name":"souta","volume":80,"pitch":100,"pan":0}]},{"code":0,"indent":0,"parameters":[]}],"moveFrequency":3,"moveRoute":{"list":[{"code":0,"parameters":[]}],"repeat":true,"skippable":false,"wait":false},"moveSpeed":3,"moveType":0,"priorityType":0,"stepAnime":false,"through":false,"trigger":3,"walkAnime":true},{"conditions":{"actorId":1,"actorValid":false,"itemId":1,"itemValid":false,"selfSwitchCh":"A","selfSwitchValid":false,"switch1Id":821,"switch1Valid":true,"switch2Id":1,"switch2Valid":false,"variableId":1,"variableValid":false,"variableValue":0},"directionFix":false,"image":{"characterIndex":0,"characterName":"","direction":2,"pattern":0,"tileId":0},"list":[{"code":117,"indent":0,"parameters":[18]},{"code":241,"indent":0,"parameters":[{"name":"ithukusimu","volume":80,"pitch":100,"pan":0}]},{"code":356,"indent":0,"parameters":["MSGSE TALK CLEAR"]},{"code":356,"indent":0,"parameters":["NameBoxReset"]},{"code":101,"indent":0,"parameters":["",0,2,1]},{"code":401,"indent":0,"parameters":["Канна всегда была со своей старшей сестрой."]},{"code":101,"indent":0,"parameters":["",0,2,1]},{"code":401,"indent":0,"parameters":["\\.Потому что очень любила её..."]},{"code":101,"indent":0,"parameters":["",0,2,1]},{"code":401,"indent":0,"parameters":["\\.Но Канна только мешала ей..."]},{"code":101,"indent":0,"parameters":["",0,2,1]},{"code":401,"indent":0,"parameters":["\\.И даже в самый важный момент"]},{"code":401,"indent":0,"parameters":["она не смогла ничего сделать."]},{"code":101,"indent":0,"parameters":["",0,2,1]},{"code":401,"indent":0,"parameters":["\\.И она думала, что её возненавидели..."]},{"code":231,"indent":0,"parameters":[1,"sumaho2",0,0,0,0,100,100,0,0]},{"code":232,"indent":0,"parameters":[1,0,0,0,0,0,100,100,255,0,60,true]},{"code":101,"indent":0,"parameters":["",0,1,1]},{"code":401,"indent":0,"parameters":["Но сообщение... напомнило ей."]},{"code":101,"indent":0,"parameters":["",0,1,1]},{"code":401,"indent":0,"parameters":["\\.Что старшая сестрёнка присматривает за ней..."]},{"code":101,"indent":0,"parameters":["",0,1,1]},{"code":401,"indent":0,"parameters":["\\.Что она должна быть сильной..."]},{"code":101,"indent":0,"parameters":["",0,1,1]},{"code":401,"indent":0,"parameters":["\\.Но..."]},{"code":242,"indent":0,"parameters":[2]},{"code":101,"indent":0,"parameters":["",0,1,1]},{"code":401,"indent":0,"parameters":["\\.На самом деле она знала..."]},{"code":232,"indent":0,"parameters":[1,0,0,0,0,0,100,100,0,0,60,false]},{"code":101,"indent":0,"parameters":["",0,1,1]},{"code":401,"indent":0,"parameters":["\\.Что то сообщение написала не её сестра..."]},{"code":101,"indent":0,"parameters":["",0,1,1]},{"code":401,"indent":0,"parameters":["\\...."]},{"code":231,"indent":0,"parameters":[31,"cara5-4",1,0,408,312,100,100,0,0]},{"code":232,"indent":0,"parameters":[31,0,1,0,408,312,100,100,255,0,90,true]},{"code":101,"indent":0,"parameters":["",0,1,2]},{"code":401,"indent":0,"parameters":["...Рядом были люди, которые хотели защитить Канну."]},{"code":101,"indent":0,"parameters":["",0,1,2]},{"code":401,"indent":0,"parameters":["\\.Которые старались помочь ей."]},{"code":232,"indent":0,"parameters":[31,0,1,0,408,312,100,100,0,0,60,true]},{"code":101,"indent":0,"parameters":["",0,1,1]},{"code":401,"indent":0,"parameters":["\\.Поэтому... она больше не хочет, чтобы кто-то умирал."]},{"code":101,"indent":0,"parameters":["",0,1,1]},{"code":401,"indent":0,"parameters":["\\.Потому что... они все такие хорошие..."]},{"code":356,"indent":0,"parameters":["MSGSE TALK DEFAULT"]},{"code":232,"indent":0,"parameters":[31,0,1,0,408,312,100,100,0,0,60,true]},{"code":235,"indent":0,"parameters":[31]},{"code":230,"indent":0,"parameters":[90]},{"code":250,"indent":0,"parameters":[{"name":"sceneswitch2","volume":100,"pitch":80,"pan":0}]},{"code":231,"indent":0,"parameters":[52,"title",1,0,408,294,100,100,0,0]},{"code":232,"indent":0,"parameters":[52,0,1,0,408,294,100,100,255,0,30,true]},{"code":230,"indent":0,"parameters":[130]},{"code":232,"indent":0,"parameters":[52,0,1,0,408,294,100,100,0,0,30,true]},{"code":235,"indent":0,"parameters":[52]},{"code":230,"indent":0,"parameters":[60]},{"code":356,"indent":0,"parameters":["NameBoxReset"]},{"code":221,"indent":0,"parameters":[]},{"code":201,"indent":0,"parameters":[0,184,0,0,0,0]},{"code":231,"indent":0,"parameters":[14,"menu",1,0,106,572,100,100,255,0]},{"code":356,"indent":0,"parameters":["P_CALL_CE 14 8 1 ON"]},{"code":230,"indent":0,"parameters":[90]},{"code":222,"indent":0,"parameters":[]},{"code":230,"indent":0,"parameters":[30]},{"code":231,"indent":0,"parameters":[31,"cara15-1",1,0,408,312,100,100,0,0]},{"code":232,"indent":0,"parameters":[31,0,1,0,408,312,100,100,255,0,60,true]},{"code":250,"indent":0,"parameters":[{"name":"Accent21-1","volume":90,"pitch":100,"pan":0}]},{"code":224,"indent":0,"parameters":[[255,255,255,170],60,false]},{"code":356,"indent":0,"parameters":["NameBoxSet Сафалин"]},{"code":101,"indent":0,"parameters":["",0,0,2]},{"code":401,"indent":0,"parameters":["\"Внимание... Скоро этаж будет закрыт.\""]},{"code":231,"indent":0,"parameters":[31,"cara15-2",1,0,408,312,100,100,255,0]},{"code":101,"indent":0,"parameters":["",0,0,2]},{"code":401,"indent":0,"parameters":["\\.\"Если вы не перейдёте на следующий этаж"]},{"code":401,"indent":0,"parameters":[" в течение 5 минут, ваши ошейники активируются...\""]},{"code":356,"indent":0,"parameters":["NameBoxSet Сара"]},{"code":101,"indent":0,"parameters":["",0,0,2]},{"code":401,"indent":0,"parameters":["\\.\"Да, да... Я знаю.\""]},{"code":231,"indent":0,"parameters":[31,"cara15-3",1,0,408,312,100,100,255,0]},{"code":356,"indent":0,"parameters":["NameBoxSet Сафалин"]},{"code":101,"indent":0,"parameters":["",0,0,2]},{"code":401,"indent":0,"parameters":["\\.\"?..\""]},{"code":231,"indent":0,"parameters":[31,"cara15-1",1,0,408,312,100,100,255,0]},{"code":356,"indent":0,"parameters":["NameBoxSet Сафалин"]},{"code":101,"indent":0,"parameters":["",0,0,2]},{"code":401,"indent":0,"parameters":["\\.\"Мисс Сара, неужели вы...\""]},{"code":231,"indent":0,"parameters":[31,"cara15-3",1,0,408,312,100,100,255,0]},{"code":250,"indent":0,"parameters":[{"name":"se_maoudamashii_magical14","volume":90,"pitch":100,"pan":0}]},{"code":224,"indent":0,"parameters":[[255,255,255,170],60,false]},{"code":101,"indent":0,"parameters":["",0,0,2]},{"code":401,"indent":0,"parameters":["\\.\"Излечились?..\""]},{"code":356,"indent":0,"parameters":["NameBoxSet Сара"]},{"code":101,"indent":0,"parameters":["",0,0,2]},{"code":401,"indent":0,"parameters":["\\.\"...Ты о галлюцинациях?\""]},{"code":231,"indent":0,"parameters":[50,"1an",1,0,408,312,2000,2000,0,0]},{"code":231,"indent":0,"parameters":[51,"saikai2",0,0,0,0,100,100,0,0]},{"code":232,"indent":0,"parameters":[50,0,1,0,408,312,2000,2000,255,0,60,false]},{"code":232,"indent":0,"parameters":[51,0,0,0,0,0,100,100,255,0,60,true]},{"code":230,"indent":0,"parameters":[30]},{"code":356,"indent":0,"parameters":["NameBoxSet Сара"]},{"code":101,"indent":0,"parameters":["",0,0,2]},{"code":401,"indent":0,"parameters":["\"Мне словно снился ужасный сон...\""]},{"code":101,"indent":0,"parameters":["",0,0,2]},{"code":401,"indent":0,"parameters":["\\.\"Я пытала себя галлюцинациями,"]},{"code":401,"indent":0,"parameters":[" которые сама же и создала.\""]},{"code":232,"indent":0,"parameters":[51,0,0,0,0,0,100,100,0,0,30,false]},{"code":232,"indent":0,"parameters":[50,0,1,0,408,312,2000,2000,0,0,30,true]},{"code":235,"indent":0,"parameters":[50]},{"code":235,"indent":0,"parameters":[51]},{"code":250,"indent":0,"parameters":[{"name":"sceneswitch2","volume":90,"pitch":100,"pan":0}]},{"code":224,"indent":0,"parameters":[[255,255,255,170],60,false]},{"code":101,"indent":0,"parameters":["",0,0,2]},{"code":401,"indent":0,"parameters":["\"Но я проснулась.\""]},{"code":231,"indent":0,"parameters":[31,"cara0-3",1,0,408,312,100,100,255,0]},{"code":241,"indent":0,"parameters":[{"name":"samuraionnna","volume":70,"pitch":100,"pan":0}]},{"code":250,"indent":0,"parameters":[{"name":"flash-of-light-3","volume":90,"pitch":100,"pan":0}]},{"code":224,"indent":0,"parameters":[[255,255,255,170],60,false]},{"code":101,"indent":0,"parameters":["",0,0,2]},{"code":401,"indent":0,"parameters":["\\.\"Я... нет, мы... вам не проиграем!\""]},{"code":231,"indent":0,"parameters":[31,"cara15-7",1,0,408,312,100,100,255,0]},{"code":356,"indent":0,"parameters":["NameBoxSet Сафалин"]},{"code":101,"indent":0,"parameters":["",0,0,2]},{"code":401,"indent":0,"parameters":["\\.\"...\""]},{"code":231,"indent":0,"parameters":[31,"cara15-1",1,0,408,312,100,100,255,0]},{"code":101,"indent":0,"parameters":["",0,0,2]},{"code":401,"indent":0,"parameters":["\\.\"...Вот как.\""]},{"code":231,"indent":0,"parameters":[31,"cara15-4",1,0,408,312,100,100,255,0]},{"code":101,"indent":0,"parameters":["",0,0,2]},{"code":401,"indent":0,"parameters":["\\.\"Тогда желаю удачи... мисс Сара.\""]},{"code":232,"indent":0,"parameters":[31,0,1,0,408,312,100,100,0,0,60,true]},{"code":231,"indent":0,"parameters":[31,"cara2-1",1,0,408,312,100,100,0,0]},{"code":232,"indent":0,"parameters":[31,0,1,0,408,312,100,100,255,0,30,true]},{"code":250,"indent":0,"parameters":[{"name":"Accent21-1","volume":90,"pitch":100,"pan":0}]},{"code":224,"indent":0,"parameters":[[255,255,255,170],60,false]},{"code":356,"indent":0,"parameters":["NameBoxSet Кейджи"]},{"code":101,"indent":0,"parameters":["",0,0,2]},{"code":401,"indent":0,"parameters":["\"Как я и ожидал..."]},{"code":401,"indent":0,"parameters":[" Тебя сложно сломить, Сара.\""]},{"code":356,"indent":0,"parameters":["NameBoxSet Сара"]},{"code":101,"indent":0,"parameters":["",0,0,2]},{"code":401,"indent":0,"parameters":["\\.\"Это не только моя заслуга...\""]},{"code":231,"indent":0,"parameters":[31,"cara2-2",1,0,408,312,100,100,255,0]},{"code":250,"indent":0,"parameters":[{"name":"Accent28-1","volume":90,"pitch":100,"pan":0}]},{"code":224,"indent":0,"parameters":[[255,255,255,170],60,false]},{"code":356,"indent":0,"parameters":["NameBoxSet Кейджи"]},{"code":101,"indent":0,"parameters":["",0,0,2]},{"code":401,"indent":0,"parameters":["\\.\"...Ты говоришь о Соу.\""]},{"code":231,"indent":0,"parameters":[31,"cara3-20",1,0,408,312,100,100,255,0]},{"code":356,"indent":0,"parameters":["NameBoxSet Канна"]},{"code":101,"indent":0,"parameters":["",0,0,2]},{"code":401,"indent":0,"parameters":["\\.\"..........\""]},{"code":231,"indent":0,"parameters":[31,"cara4-3",1,0,408,312,100,100,255,0]},{"code":356,"indent":0,"parameters":["NameBoxSet Кью-таро"]},{"code":101,"indent":0,"parameters":["",0,0,2]},{"code":401,"indent":0,"parameters":["\\.\"Он вообще до самого конца меня подбешивал."]},{"code":401,"indent":0,"parameters":[" Потому шо продолжал использовать нас и врать...\""]},{"code":231,"indent":0,"parameters":[31,"cara3-20",1,0,408,312,100,100,255,0]},{"code":250,"indent":0,"parameters":[{"name":"se_maoudamashii_magical14","volume":90,"pitch":100,"pan":0}]},{"code":224,"indent":0,"parameters":[[255,255,255,170],60,false]},{"code":356,"indent":0,"parameters":["NameBoxSet Канна"]},{"code":101,"indent":0,"parameters":["",0,0,2]},{"code":401,"indent":0,"parameters":["\\.\"Но... на самом деле он пытался защитить Канну.\""]},{"code":111,"indent":0,"parameters":[0,642,0]},{"code":231,"indent":1,"parameters":[31,"cara6-7",1,0,408,312,100,100,255,0]},{"code":356,"indent":1,"parameters":["NameBoxSet Реко"]},{"code":101,"indent":1,"parameters":["",0,0,2]},{"code":401,"indent":1,"parameters":["\\.\"Наверное...\""]},{"code":231,"indent":1,"parameters":[31,"cara6-2",1,0,408,312,100,100,255,0]},{"code":101,"indent":1,"parameters":["",0,0,2]},{"code":401,"indent":1,"parameters":["\\.\"Канна, даже не думай снова "]},{"code":401,"indent":1,"parameters":[" жертвовать собой, лады?\""]},{"code":231,"indent":1,"parameters":[31,"cara6-4",1,0,408,312,100,100,255,0]},{"code":250,"indent":1,"parameters":[{"name":"Accent28-1","volume":90,"pitch":100,"pan":0}]},{"code":224,"indent":1,"parameters":[[255,255,255,170],60,false]},{"code":101,"indent":1,"parameters":["",0,0,2]},{"code":401,"indent":1,"parameters":["\\.\"Ты должна стать для похитителей такой же"]},{"code":401,"indent":1,"parameters":[" помехой, какой был бы Соу, понимаешь?\""]},{"code":231,"indent":1,"parameters":[31,"cara3-23",1,0,408,312,100,100,255,0]},{"code":250,"indent":1,"parameters":[{"name":"flash-of-light-3","volume":90,"pitch":100,"pan":0}]},{"code":224,"indent":1,"parameters":[[255,255,255,170],60,false]},{"code":356,"indent":1,"parameters":["NameBoxSet Канна"]},{"code":101,"indent":1,"parameters":["",0,0,2]},{"code":401,"indent":1,"parameters":["\\.\"Да!..\""]},{"code":231,"indent":1,"parameters":[31,"cara6-7",1,0,408,312,100,100,255,0]},{"code":356,"indent":1,"parameters":["NameBoxSet Реко"]},{"code":101,"indent":1,"parameters":["",0,0,2]},{"code":401,"indent":1,"parameters":["\\.\"Сделай это не только ради Соу... но и ради Нао...\""]},{"code":231,"indent":1,"parameters":[31,"cara9-3",1,0,408,312,100,100,255,0]},{"code":356,"indent":1,"parameters":["NameBoxSet Гин"]},{"code":101,"indent":1,"parameters":["",0,0,2]},{"code":401,"indent":1,"parameters":["\\.\"Точно...\""]},{"code":0,"indent":1,"parameters":[]},{"code":411,"indent":0,"parameters":[]},{"code":231,"indent":1,"parameters":[31,"cara4-7",1,0,408,312,100,100,255,0]},{"code":356,"indent":1,"parameters":["NameBoxSet Кью-таро"]},{"code":101,"indent":1,"parameters":["",0,0,2]},{"code":401,"indent":1,"parameters":["\\.\"Походу...\""]},{"code":231,"indent":1,"parameters":[31,"cara4-5",1,0,408,312,100,100,255,0]},{"code":101,"indent":1,"parameters":["",0,0,2]},{"code":401,"indent":1,"parameters":["\\.\"Те надо выжить ради него, Канна.\""]},{"code":231,"indent":1,"parameters":[31,"cara4-5",1,0,408,312,100,100,255,0]},{"code":250,"indent":1,"parameters":[{"name":"Accent28-1","volume":90,"pitch":100,"pan":0}]},{"code":224,"indent":1,"parameters":[[255,255,255,170],60,false]},{"code":101,"indent":1,"parameters":["",0,0,2]},{"code":401,"indent":1,"parameters":["\\.\"Даж не думай опять жертвовать собой!\""]},{"code":231,"indent":1,"parameters":[31,"cara3-23",1,0,408,312,100,100,255,0]},{"code":250,"indent":1,"parameters":[{"name":"flash-of-light-3","volume":90,"pitch":100,"pan":0}]},{"code":224,"indent":1,"parameters":[[255,255,255,170],60,false]},{"code":356,"indent":1,"parameters":["NameBoxSet Канна"]},{"code":101,"indent":1,"parameters":["",0,0,2]},{"code":401,"indent":1,"parameters":["\\.\"Да!..\""]},{"code":231,"indent":1,"parameters":[31,"cara9-3",1,0,408,312,100,100,255,0]},{"code":356,"indent":1,"parameters":["NameBoxSet Гин"]},{"code":101,"indent":1,"parameters":["",0,0,2]},{"code":401,"indent":1,"parameters":["\\.\"И... ради старшей сестрёнки Нао тоже...\""]},{"code":0,"indent":1,"parameters":[]},{"code":412,"indent":0,"parameters":[]},{"code":356,"indent":0,"parameters":["NameBoxSet Сара"]},{"code":101,"indent":0,"parameters":["",0,0,2]},{"code":401,"indent":0,"parameters":["\\.\\C[4](Нао...)"]},{"code":231,"indent":0,"parameters":[31,"cara2-1",1,0,408,312,100,100,255,0]},{"code":356,"indent":0,"parameters":["NameBoxSet Кейджи"]},{"code":101,"indent":0,"parameters":["",0,0,2]},{"code":401,"indent":0,"parameters":["\\.\"Поэтому мы должны приложить все усилия.\""]},{"code":111,"indent":0,"parameters":[0,642,0]},{"code":231,"indent":1,"parameters":[31,"cara2-4",1,0,408,312,100,100,255,0]},{"code":101,"indent":1,"parameters":["",0,0,2]},{"code":401,"indent":1,"parameters":["\\.\"И для начала... следующий этаж."]},{"code":401,"indent":1,"parameters":[" Будет не очень весело, если сейчас"]},{"code":401,"indent":1,"parameters":[" активируются ошейники.\""]},{"code":0,"indent":1,"parameters":[]},{"code":411,"indent":0,"parameters":[]},{"code":231,"indent":1,"parameters":[31,"cara11-3",1,0,408,312,100,100,255,0]},{"code":356,"indent":1,"parameters":["NameBoxSet Элис"]},{"code":101,"indent":1,"parameters":["",0,0,2]},{"code":401,"indent":1,"parameters":["\\.\"Тогда сейчас нам нужно отправиться на следующий"]},{"code":401,"indent":1,"parameters":[" этаж?.. Иначе активируются ошейники...\""]},{"code":0,"indent":1,"parameters":[]},{"code":412,"indent":0,"parameters":[]},{"code":231,"indent":0,"parameters":[31,"cara9-6",1,0,408,312,100,100,255,0]},{"code":250,"indent":0,"parameters":[{"name":"feed1","volume":90,"pitch":100,"pan":0}]},{"code":225,"indent":0,"parameters":[7,7,30,false]},{"code":356,"indent":0,"parameters":["NameBoxSet Гин"]},{"code":101,"indent":0,"parameters":["",0,0,2]},{"code":401,"indent":0,"parameters":["\\.\"Начнём планировать побег заново,"]},{"code":401,"indent":0,"parameters":[" когда будем на следующем этаже, мяу!\""]},{"code":231,"indent":0,"parameters":[31,"cara3-16",1,0,408,312,100,100,255,0]},{"code":250,"indent":0,"parameters":[{"name":"Accent21-1","volume":90,"pitch":100,"pan":0}]},{"code":224,"indent":0,"parameters":[[255,255,255,170],60,false]},{"code":356,"indent":0,"parameters":["NameBoxSet Канна"]},{"code":101,"indent":0,"parameters":["",0,0,2]},{"code":401,"indent":0,"parameters":["\\.\"В этот раз... В этот раз мы точно сбежим!\""]},{"code":356,"indent":0,"parameters":["NameBoxSet Сара"]},{"code":101,"indent":0,"parameters":["",0,0,2]},{"code":401,"indent":0,"parameters":["\\.\\C[4](Kaннa...)"]},{"code":101,"indent":0,"parameters":["",0,0,2]},{"code":401,"indent":0,"parameters":["\\.\\C[4](Kaнна явно изменилась...)"]},{"code":101,"indent":0,"parameters":["",0,0,2]},{"code":401,"indent":0,"parameters":["\\.\\C[4](Я могу с уверенностью сказать... "]},{"code":401,"indent":0,"parameters":[" она стала сильнее.)"]},{"code":101,"indent":0,"parameters":["",0,0,2]},{"code":401,"indent":0,"parameters":["\\.\\C[4](...)"]},{"code":250,"indent":0,"parameters":[{"name":"Accent21-1","volume":90,"pitch":100,"pan":0}]},{"code":224,"indent":0,"parameters":[[255,255,255,170],60,false]},{"code":101,"indent":0,"parameters":["",0,0,2]},{"code":401,"indent":0,"parameters":["\\.\\C[4](С каждой жертвой... мы меняемся...)"]},{"code":101,"indent":0,"parameters":["",0,0,2]},{"code":401,"indent":0,"parameters":["\\.\\C[4](Точно... Их смерти не будут напрасными!)"]},{"code":231,"indent":0,"parameters":[31,"cara0-3",1,0,408,312,100,100,255,0]},{"code":250,"indent":0,"parameters":[{"name":"Accent28-1","volume":90,"pitch":100,"pan":0}]},{"code":224,"indent":0,"parameters":[[255,255,255,170],60,false]},{"code":101,"indent":0,"parameters":["",0,0,2]},{"code":401,"indent":0,"parameters":["\\.\"Все, идём!\""]},{"code":231,"indent":0,"parameters":[31,"cara2-1",1,0,408,312,100,100,255,0]},{"code":356,"indent":0,"parameters":["NameBoxSet Кейджи"]},{"code":101,"indent":0,"parameters":["",0,0,2]},{"code":401,"indent":0,"parameters":["\\.\"Конечно. После вас, партнёр.\""]},{"code":232,"indent":0,"parameters":[31,0,1,0,408,312,100,100,0,0,30,true]},{"code":235,"indent":0,"parameters":[31]},{"code":117,"indent":0,"parameters":[13]},{"code":0,"indent":0,"parameters":[]}],"moveFrequency":3,"moveRoute":{"list":[{"code":0,"parameters":[]}],"repeat":true,"skippable":false,"wait":false},"moveSpeed":3,"moveType":0,"priorityType":0,"stepAnime":false,"through":false,"trigger":3,"walkAnime":true}],"x":1,"y":0},
{"id":2,"name":"EV002","note":"","pages":[{"conditions":{"actorId":1,"actorValid":false,"itemId":1,"itemValid":false,"selfSwitchCh":"A","selfSwitchValid":false,"switch1Id":822,"switch1Valid":true,"switch2Id":1,"switch2Valid":false,"variableId":1,"variableValid":false,"variableValue":0},"directionFix":false,"image":{"characterIndex":0,"characterName":"","direction":2,"pattern":0,"tileId":0},"list":[{"code":117,"indent":0,"parameters":[18]},{"code":356,"indent":0,"parameters":["NameBoxReset"]},{"code":101,"indent":0,"parameters":["",0,2,1]},{"code":401,"indent":0,"parameters":["バカなヤツだ…"]},{"code":101,"indent":0,"parameters":["",0,2,1]},{"code":401,"indent":0,"parameters":["\\.本当に…　バカで…　どうしようもないガキだ…"]},{"code":101,"indent":0,"parameters":["",0,2,1]},{"code":401,"indent":0,"parameters":["\\.カンナ…"]},{"code":101,"indent":0,"parameters":["",0,2,2]},{"code":401,"indent":0,"parameters":["ボクを守る…？"]},{"code":101,"indent":0,"parameters":["",0,2,0]},{"code":401,"indent":0,"parameters":["自己犠牲…？"]},{"code":101,"indent":0,"parameters":["",0,2,1]},{"code":401,"indent":0,"parameters":["誰が望んだ…　そんなこと…"]},{"code":101,"indent":0,"parameters":["",0,2,1]},{"code":401,"indent":0,"parameters":["\\.………"]},{"code":101,"indent":0,"parameters":["",0,2,1]},{"code":401,"indent":0,"parameters":["\\.もう　どうでもいい…"]},{"code":231,"indent":0,"parameters":[31,"cara19-1",1,0,408,312,100,100,0,0]},{"code":232,"indent":0,"parameters":[31,0,1,0,408,312,100,100,255,0,120,true]},{"code":101,"indent":0,"parameters":["",0,1,2]},{"code":401,"indent":0,"parameters":["\\.ヒヨリソウ…　キミも関わっているのか？"]},{"code":101,"indent":0,"parameters":["",0,1,2]},{"code":401,"indent":0,"parameters":["\\.\\C[10]だったら全部　破壊してやる"]},{"code":232,"indent":0,"parameters":[31,0,1,0,408,312,100,100,0,0,120,true]},{"code":235,"indent":0,"parameters":[31]},{"code":250,"indent":0,"parameters":[{"name":"sceneswitch2","volume":100,"pitch":80,"pan":0}]},{"code":231,"indent":0,"parameters":[52,"title",1,0,408,294,100,100,0,0]},{"code":232,"indent":0,"parameters":[52,0,1,0,408,294,100,100,255,0,30,true]},{"code":230,"indent":0,"parameters":[130]},{"code":232,"indent":0,"parameters":[52,0,1,0,408,294,100,100,0,0,30,true]},{"code":235,"indent":0,"parameters":[52]},{"code":230,"indent":0,"parameters":[60]},{"code":356,"indent":0,"parameters":["NameBoxReset"]},{"code":221,"indent":0,"parameters":[]},{"code":201,"indent":0,"parameters":[0,186,0,0,0,0]},{"code":231,"indent":0,"parameters":[14,"menu",1,0,106,572,100,100,255,0]},{"code":356,"indent":0,"parameters":["P_CALL_CE 14 8 1 ON"]},{"code":230,"indent":0,"parameters":[90]},{"code":222,"indent":0,"parameters":[]},{"code":241,"indent":0,"parameters":[{"name":"Tsurugi","volume":80,"pitch":100,"pan":0}]},{"code":230,"indent":0,"parameters":[30]},{"code":356,"indent":0,"parameters":["MSGSE TALK select05 70 50 0"]},{"code":356,"indent":0,"parameters":["NameBoxSet Speaker"]},{"code":101,"indent":0,"parameters":["",0,0,2]},{"code":401,"indent":0,"parameters":["\\.\\C[5]「参加者の皆様へのお知らせです」"]},{"code":101,"indent":0,"parameters":["",0,0,2]},{"code":401,"indent":0,"parameters":["\\.\\C[5]「このフロアは５分後に閉館されます」"]},{"code":101,"indent":0,"parameters":["",0,0,2]},{"code":401,"indent":0,"parameters":["\\.\\C[5]「急いでロビーから上の階へ上がってください」"]},{"code":356,"indent":0,"parameters":["MSGSE TALK DEFAULT"]},{"code":231,"indent":0,"parameters":[31,"cara4-6",1,0,408,312,100,100,0,0]},{"code":232,"indent":0,"parameters":[31,0,1,0,408,312,100,100,255,0,30,true]},{"code":250,"indent":0,"parameters":[{"name":"feed1","volume":90,"pitch":100,"pan":0}]},{"code":225,"indent":0,"parameters":[7,7,30,false]},{"code":356,"indent":0,"parameters":["NameBoxSet Кью-таро"]},{"code":101,"indent":0,"parameters":["",0,0,2]},{"code":401,"indent":0,"parameters":["「まずいぜよ…サラ"]},{"code":401,"indent":0,"parameters":["　時間までに上に行かねえと　首輪が…」"]},{"code":250,"indent":0,"parameters":[{"name":"Accent21-1","volume":90,"pitch":100,"pan":0}]},{"code":224,"indent":0,"parameters":[[255,255,255,170],60,false]},{"code":356,"indent":0,"parameters":["NameBoxSet Сара"]},{"code":101,"indent":0,"parameters":["",0,0,2]},{"code":401,"indent":0,"parameters":["\\C[4]（でも…ソウさんがどこにもいない…！）"]},{"code":231,"indent":0,"parameters":[31,"cara9-3",1,0,408,312,100,100,255,0]},{"code":356,"indent":0,"parameters":["NameBoxSet Гин"]},{"code":101,"indent":0,"parameters":["",0,0,2]},{"code":401,"indent":0,"parameters":["\\.「先に上に行ったのかニャン…」"]},{"code":231,"indent":0,"parameters":[31,"cara2-6",1,0,408,312,100,100,255,0]},{"code":356,"indent":0,"parameters":["NameBoxSet Кейджи"]},{"code":101,"indent":0,"parameters":["",0,0,2]},{"code":401,"indent":0,"parameters":["\\.「…おまわりさん達と"]},{"code":401,"indent":0,"parameters":["　顔を合わせたくないのかもしれないねー…」"]},{"code":232,"indent":0,"parameters":[31,0,1,0,408,312,100,100,0,0,30,true]},{"code":356,"indent":0,"parameters":["NameBoxSet Сара"]},{"code":101,"indent":0,"parameters":["",0,0,2]},{"code":401,"indent":0,"parameters":["\\.\\C[4]（先に上へ行くべきか…？）"]},{"code":231,"indent":0,"parameters":[31,"cara5-2",1,0,408,312,100,100,0,0]},{"code":232,"indent":0,"parameters":[31,0,1,0,408,312,100,100,255,0,30,true]},{"code":250,"indent":0,"parameters":[{"name":"Accent28-1","volume":90,"pitch":100,"pan":0}]},{"code":224,"indent":0,"parameters":[[255,255,255,170],60,false]},{"code":356,"indent":0,"parameters":["NameBoxSet Соу"]},{"code":101,"indent":0,"parameters":["",0,0,2]},{"code":401,"indent":0,"parameters":["「どうかした？　みんな」"]},{"code":231,"indent":0,"parameters":[31,"cara2-2",1,0,408,312,100,100,255,0]},{"code":356,"indent":0,"parameters":["NameBoxSet Кейджи"]},{"code":101,"indent":0,"parameters":["",0,0,2]},{"code":401,"indent":0,"parameters":["\\.「ソウ…」"]},{"code":111,"indent":0,"parameters":[0,642,0]},{"code":231,"indent":1,"parameters":[31,"cara6-10",1,0,408,312,100,100,255,0]},{"code":356,"indent":1,"parameters":["NameBoxSet Реко"]},{"code":101,"indent":1,"parameters":["",0,0,2]},{"code":401,"indent":1,"parameters":["\\.「……」"]},{"code":0,"indent":1,"parameters":[]},{"code":411,"indent":0,"parameters":[]},{"code":231,"indent":1,"parameters":[31,"cara11-18",1,0,408,312,100,100,255,0]},{"code":356,"indent":1,"parameters":["NameBoxSet Элис"]},{"code":101,"indent":1,"parameters":["",0,0,2]},{"code":401,"indent":1,"parameters":["\\.「……」"]},{"code":0,"indent":1,"parameters":[]},{"code":412,"indent":0,"parameters":[]},{"code":231,"indent":0,"parameters":[31,"cara5-18",1,0,408,312,100,100,255,0]},{"code":356,"indent":0,"parameters":["NameBoxSet Соу"]},{"code":101,"indent":0,"parameters":["",0,0,2]},{"code":401,"indent":0,"parameters":["\\.「怖い顔しないでよ　ボクらは仲間でしょ？」"]},{"code":231,"indent":0,"parameters":[31,"cara4-7",1,0,408,312,100,100,255,0]},{"code":250,"indent":0,"parameters":[{"name":"se_maoudamashii_magical14","volume":90,"pitch":100,"pan":0}]},{"code":224,"indent":0,"parameters":[[255,255,255,170],60,false]},{"code":356,"indent":0,"parameters":["NameBoxSet Кью-таро"]},{"code":101,"indent":0,"parameters":["",0,0,2]},{"code":401,"indent":0,"parameters":["\\.「…お前さんこそ…なんでそんな涼しい顔ができるぜよ…」"]},{"code":231,"indent":0,"parameters":[31,"cara5-19",1,0,408,312,100,100,255,0]},{"code":356,"indent":0,"parameters":["NameBoxSet Соу"]},{"code":101,"indent":0,"parameters":["",0,0,2]},{"code":401,"indent":0,"parameters":["\\.「あぁ…　カンナの事…？」"]},{"code":231,"indent":0,"parameters":[31,"cara5-15",1,0,408,312,100,100,255,0]},{"code":101,"indent":0,"parameters":["",0,0,2]},{"code":401,"indent":0,"parameters":["\\.「残念だよ…　カンナがあの時　本当に\\C[10]身代\\C[0]を持ってたら"]},{"code":401,"indent":0,"parameters":["　ボクら２人で脱出するはずだった」"]},{"code":231,"indent":0,"parameters":[31,"cara5-18",1,0,408,312,100,100,255,0]},{"code":250,"indent":0,"parameters":[{"name":"horror_piano chord3","volume":90,"pitch":100,"pan":0}]},{"code":224,"indent":0,"parameters":[[255,0,0,170],60,false]},{"code":101,"indent":0,"parameters":["",0,0,2]},{"code":401,"indent":0,"parameters":["\\.\\C[10]「利用しそこなって…残念だよ」"]},{"code":231,"indent":0,"parameters":[31,"cara9-4",1,0,408,312,100,100,255,0]},{"code":356,"indent":0,"parameters":["NameBoxSet Гин"]},{"code":101,"indent":0,"parameters":["",0,0,2]},{"code":401,"indent":0,"parameters":["\\.\"..........\""]},{"code":231,"indent":0,"parameters":[31,"cara2-1",1,0,408,312,100,100,255,0]},{"code":250,"indent":0,"parameters":[{"name":"sceneswitch2","volume":90,"pitch":100,"pan":0}]},{"code":224,"indent":0,"parameters":[[255,255,255,170],60,false]},{"code":356,"indent":0,"parameters":["NameBoxSet Кейджи"]},{"code":101,"indent":0,"parameters":["",0,0,2]},{"code":401,"indent":0,"parameters":["\\.「ククク…」"]},{"code":231,"indent":0,"parameters":[31,"cara5-17",1,0,408,312,100,100,255,0]},{"code":356,"indent":0,"parameters":["NameBoxSet Соу"]},{"code":101,"indent":0,"parameters":["",0,0,2]},{"code":401,"indent":0,"parameters":["\\.「何がおかしいの…？」"]},{"code":231,"indent":0,"parameters":[31,"cara2-1",1,0,408,312,100,100,255,0]},{"code":250,"indent":0,"parameters":[{"name":"se_maoudamashii_magical14","volume":90,"pitch":100,"pan":0}]},{"code":224,"indent":0,"parameters":[[255,255,255,170],60,false]},{"code":356,"indent":0,"parameters":["NameBoxSet Кейджи"]},{"code":101,"indent":0,"parameters":["",0,0,2]},{"code":401,"indent":0,"parameters":["\\.「哀れだねー…　もしそんな世界があれば"]},{"code":401,"indent":0,"parameters":["　カンナちゃんが選ぶのは　キミじゃない　サラちゃんだ」"]},{"code":231,"indent":0,"parameters":[31,"cara5-5",1,0,408,312,100,100,255,0]},{"code":356,"indent":0,"parameters":["NameBoxSet Соу"]},{"code":101,"indent":0,"parameters":["",0,0,2]},{"code":401,"indent":0,"parameters":["\\.「……！」"]},{"code":231,"indent":0,"parameters":[31,"cara2-1",1,0,408,312,100,100,255,0]},{"code":356,"indent":0,"parameters":["NameBoxSet Кейджи"]},{"code":101,"indent":0,"parameters":["",0,0,2]},{"code":401,"indent":0,"parameters":["\\.「ククク…自分が選ばれるとでも思ってたのかい？」"]},{"code":231,"indent":0,"parameters":[31,"cara5-32",1,0,408,312,100,100,255,0]},{"code":356,"indent":0,"parameters":["NameBoxSet Соу"]},{"code":101,"indent":0,"parameters":["",0,0,2]},{"code":401,"indent":0,"parameters":["\\.「黙れ…!!　ケイジ…!!」"]},{"code":231,"indent":0,"parameters":[31,"cara5-30",1,0,408,312,100,100,255,0]},{"code":101,"indent":0,"parameters":["",0,0,2]},{"code":401,"indent":0,"parameters":["\\.「そんなこと…わかってる…!!"]},{"code":401,"indent":0,"parameters":["　クソッ…!!　カンナは…!!」"]},{"code":231,"indent":0,"parameters":[31,"cara2-3",1,0,408,312,100,100,255,0]},{"code":250,"indent":0,"parameters":[{"name":"Accent28-1","volume":90,"pitch":100,"pan":0}]},{"code":224,"indent":0,"parameters":[[255,255,255,170],60,false]},{"code":356,"indent":0,"parameters":["NameBoxSet Кейджи"]},{"code":101,"indent":0,"parameters":["",0,0,2]},{"code":401,"indent":0,"parameters":["\\.「もうウソはよせ　ソウ」"]},{"code":101,"indent":0,"parameters":["",0,0,2]},{"code":401,"indent":0,"parameters":["\\.「キミは命がけでカンナちゃんを守り…"]},{"code":401,"indent":0,"parameters":["　オレ達はそれを妨害した」"]},{"code":231,"indent":0,"parameters":[31,"cara5-37",1,0,408,312,100,100,255,0]},{"code":356,"indent":0,"parameters":["NameBoxSet Соу"]},{"code":101,"indent":0,"parameters":["",0,0,2]},{"code":401,"indent":0,"parameters":["\\.\"..........\""]},{"code":231,"indent":0,"parameters":[31,"cara2-3",1,0,408,312,100,100,255,0]},{"code":250,"indent":0,"parameters":[{"name":"Accent21-1","volume":90,"pitch":100,"pan":0}]},{"code":224,"indent":0,"parameters":[[255,255,255,170],60,false]},{"code":356,"indent":0,"parameters":["NameBoxSet Кейджи"]},{"code":101,"indent":0,"parameters":["",0,0,2]},{"code":401,"indent":0,"parameters":["\\.「…殺したいほど憎んでるはずだ」"]},{"code":231,"indent":0,"parameters":[31,"cara2-4",1,0,408,312,100,100,255,0]},{"code":101,"indent":0,"parameters":["",0,0,2]},{"code":401,"indent":0,"parameters":["\\.「それでも…協力しあわないといけない」"]},{"code":231,"indent":0,"parameters":[31,"cara5-37",1,0,408,312,100,100,255,0]},{"code":250,"indent":0,"parameters":[{"name":"sceneswitch2","volume":90,"pitch":100,"pan":0}]},{"code":224,"indent":0,"parameters":[[255,255,255,170],60,false]},{"code":356,"indent":0,"parameters":["NameBoxSet Соу"]},{"code":101,"indent":0,"parameters":["",0,0,2]},{"code":401,"indent":0,"parameters":["\\.「…話にならないね」"]},{"code":231,"indent":0,"parameters":[31,"cara5-18",1,0,408,312,100,100,255,0]},{"code":101,"indent":0,"parameters":["",0,0,2]},{"code":401,"indent":0,"parameters":["\\.「もういい　早く次のフロアへ行こうよ」"]},{"code":231,"indent":0,"parameters":[31,"cara2-3",1,0,408,312,100,100,255,0]},{"code":356,"indent":0,"parameters":["NameBoxSet Кейджи"]},{"code":101,"indent":0,"parameters":["",0,0,2]},{"code":401,"indent":0,"parameters":["\\.「ソウ…」"]},{"code":231,"indent":0,"parameters":[31,"cara5-19",1,0,408,312,100,100,255,0]},{"code":356,"indent":0,"parameters":["NameBoxSet Соу"]},{"code":101,"indent":0,"parameters":["",0,0,2]},{"code":401,"indent":0,"parameters":["\\.「…ケイジさんこそ　ボクに死んで欲しいと"]},{"code":401,"indent":0,"parameters":["　思ってたじゃないか」"]},{"code":231,"indent":0,"parameters":[31,"cara2-16",1,0,408,312,100,100,255,0]},{"code":356,"indent":0,"parameters":["NameBoxSet Кейджи"]},{"code":101,"indent":0,"parameters":["",0,0,2]},{"code":401,"indent":0,"parameters":["\\.「今はもう…違う」"]},{"code":231,"indent":0,"parameters":[31,"cara5-15",1,0,408,312,100,100,255,0]},{"code":356,"indent":0,"parameters":["NameBoxSet Соу"]},{"code":101,"indent":0,"parameters":["",0,0,2]},{"code":401,"indent":0,"parameters":["\\.\"..........\""]},{"code":250,"indent":0,"parameters":[{"name":"asioto2","volume":90,"pitch":100,"pan":0}]},{"code":232,"indent":0,"parameters":[31,0,1,0,408,312,100,100,0,0,60,true]},{"code":235,"indent":0,"parameters":[31]},{"code":251,"indent":0,"parameters":[]},{"code":111,"indent":0,"parameters":[0,642,0]},{"code":231,"indent":1,"parameters":[31,"cara6-6",1,0,408,312,100,100,0,0]},{"code":232,"indent":1,"parameters":[31,0,1,0,408,312,100,100,255,0,30,true]},{"code":356,"indent":1,"parameters":["NameBoxSet Реко"]},{"code":101,"indent":1,"parameters":["",0,0,2]},{"code":401,"indent":1,"parameters":["「私達も行こう　アイツの事は…また後だ」"]},{"code":0,"indent":1,"parameters":[]},{"code":411,"indent":0,"parameters":[]},{"code":231,"indent":1,"parameters":[31,"cara4-8",1,0,408,312,100,100,0,0]},{"code":232,"indent":1,"parameters":[31,0,1,0,408,312,100,100,255,0,30,true]},{"code":356,"indent":1,"parameters":["NameBoxSet Кью-таро"]},{"code":101,"indent":1,"parameters":["",0,0,2]},{"code":401,"indent":1,"parameters":["「オレ達も行くぜよ…　今は自分達の身の事を…」"]},{"code":0,"indent":1,"parameters":[]},{"code":412,"indent":0,"parameters":[]},{"code":232,"indent":0,"parameters":[31,0,1,0,408,312,100,100,0,0,30,true]},{"code":235,"indent":0,"parameters":[31]},{"code":117,"indent":0,"parameters":[13]},{"code":0,"indent":0,"parameters":[]}],"moveFrequency":3,"moveRoute":{"list":[{"code":0,"parameters":[]}],"repeat":true,"skippable":false,"wait":false},"moveSpeed":3,"moveType":0,"priorityType":0,"stepAnime":false,"through":false,"trigger":0,"walkAnime":true},{"conditions":{"actorId":1,"actorValid":false,"itemId":1,"itemValid":false,"selfSwitchCh":"A","selfSwitchValid":false,"switch1Id":821,"switch1Valid":false,"switch2Id":1,"switch2Valid":false,"variableId":1,"variableValid":false,"variableValue":0},"directionFix":false,"image":{"characterIndex":0,"characterName":"","direction":2,"pattern":0,"tileId":0},"list":[{"code":117,"indent":0,"parameters":[18]},{"code":241,"indent":0,"parameters":[{"name":"ithukusimu","volume":90,"pitch":100,"pan":0}]},{"code":356,"indent":0,"parameters":["NameBoxReset"]},{"code":101,"indent":0,"parameters":["",0,2,1]},{"code":401,"indent":0,"parameters":["いつも…お姉ちゃんに守られてた"]},{"code":101,"indent":0,"parameters":["",0,2,1]},{"code":401,"indent":0,"parameters":["カンナは何もできなくて…"]},{"code":101,"indent":0,"parameters":["",0,2,1]},{"code":401,"indent":0,"parameters":["誰も救えなくて…"]},{"code":101,"indent":0,"parameters":["",0,2,1]},{"code":401,"indent":0,"parameters":["迷惑ばかり…"]},{"code":101,"indent":0,"parameters":["",0,1,1]},{"code":401,"indent":0,"parameters":["でも　あのメッセージを読んで…救われた"]},{"code":101,"indent":0,"parameters":["",0,1,1]},{"code":401,"indent":0,"parameters":["お姉ちゃんはきっと　見守ってくれてるって…"]},{"code":101,"indent":0,"parameters":["",0,1,1]},{"code":401,"indent":0,"parameters":["けどね…"]},{"code":242,"indent":0,"parameters":[2]},{"code":101,"indent":0,"parameters":["",0,1,1]},{"code":401,"indent":0,"parameters":["本当は…知ってるの…"]},{"code":101,"indent":0,"parameters":["",0,1,1]},{"code":401,"indent":0,"parameters":["あの文章は　お姉ちゃんが書いた物じゃないって…"]},{"code":101,"indent":0,"parameters":["",0,1,1]},{"code":401,"indent":0,"parameters":["…"]},{"code":101,"indent":0,"parameters":["",0,1,1]},{"code":401,"indent":0,"parameters":["だからもう…誰にも死んで欲しくない"]},{"code":101,"indent":0,"parameters":["",0,1,1]},{"code":401,"indent":0,"parameters":["みんな…優しい人達だから…"]},{"code":231,"indent":0,"parameters":[31,"cara4-6",1,0,408,312,100,100,0,0]},{"code":232,"indent":0,"parameters":[31,0,1,0,408,312,100,100,255,0,30,true]},{"code":356,"indent":0,"parameters":["NameBoxSet Кью-таро"]},{"code":101,"indent":0,"parameters":["",0,0,2]},{"code":401,"indent":0,"parameters":["「グッ…！　行くしかねえのか…？"]},{"code":401,"indent":0,"parameters":["　次の階に…」"]},{"code":231,"indent":0,"parameters":[31,"cara2-16",1,0,408,312,100,100,255,0]},{"code":356,"indent":0,"parameters":["NameBoxSet Кейджи"]},{"code":101,"indent":0,"parameters":["",0,0,2]},{"code":401,"indent":0,"parameters":["\\.「仕方ないさ…　脱出の作戦を練る時間はない」"]},{"code":111,"indent":0,"parameters":[0,642,0]},{"code":231,"indent":1,"parameters":[31,"cara6-8",1,0,408,312,100,100,255,0]},{"code":356,"indent":1,"parameters":["NameBoxSet Реко"]},{"code":101,"indent":1,"parameters":["",0,0,2]},{"code":401,"indent":1,"parameters":["\\.「私達には　ハッキングなんてできねえしな…」"]},{"code":0,"indent":1,"parameters":[]},{"code":411,"indent":0,"parameters":[]},{"code":231,"indent":1,"parameters":[31,"cara11-18",1,0,408,312,100,100,255,0]},{"code":356,"indent":1,"parameters":["NameBoxSet Элис"]},{"code":101,"indent":1,"parameters":["",0,0,2]},{"code":401,"indent":1,"parameters":["\\.「チッ…　ガシューの死程度じゃ"]},{"code":401,"indent":1,"parameters":["　管理体制に不備も生まれないのか…！」"]},{"code":0,"indent":1,"parameters":[]},{"code":412,"indent":0,"parameters":[]},{"code":231,"indent":0,"parameters":[31,"cara9-6",1,0,408,312,100,100,255,0]},{"code":356,"indent":0,"parameters":["NameBoxSet Гин"]},{"code":101,"indent":0,"parameters":["",0,0,2]},{"code":401,"indent":0,"parameters":["\\.「だったら次の階で　別の脱出作戦を考えれば"]},{"code":401,"indent":0,"parameters":["　良いニャン！」"]},{"code":231,"indent":0,"parameters":[31,"cara3-16",1,0,408,312,100,100,255,0]},{"code":356,"indent":0,"parameters":["NameBoxSet Канна"]},{"code":101,"indent":0,"parameters":["",0,0,2]},{"code":401,"indent":0,"parameters":["\\.「その通りです！"]},{"code":401,"indent":0,"parameters":["　カンナ達が諦めるわけにはいきません…!!」"]},{"code":356,"indent":0,"parameters":["NameBoxSet Сара"]},{"code":101,"indent":0,"parameters":["",0,0,2]},{"code":401,"indent":0,"parameters":["\\.\\C[4]（そうさ…みんなの死を無駄にしたくない…！）"]},{"code":231,"indent":0,"parameters":[31,"cara0-3",1,0,408,312,100,100,255,0]},{"code":101,"indent":0,"parameters":["",0,0,2]},{"code":401,"indent":0,"parameters":["\\.「行きましょう…みなさん！」"]},{"code":231,"indent":0,"parameters":[31,"cara2-1",1,0,408,312,100,100,255,0]},{"code":356,"indent":0,"parameters":["NameBoxSet Кейджи"]},{"code":101,"indent":0,"parameters":["",0,0,2]},{"code":401,"indent":0,"parameters":["\\.「ククク…やっぱりサラちゃんの一喝は効くねー…」"]},{"code":231,"indent":0,"parameters":[31,"cara9-11",1,0,408,312,100,100,255,0]},{"code":356,"indent":0,"parameters":["NameBoxSet Гин"]},{"code":101,"indent":0,"parameters":["",0,0,2]},{"code":401,"indent":0,"parameters":["\\.「やってやるニャン～!!」"]},{"code":232,"indent":0,"parameters":[31,0,1,0,408,312,100,100,0,0,30,true]},{"code":235,"indent":0,"parameters":[31]},{"code":117,"indent":0,"parameters":[13]},{"code":0,"indent":0,"parameters":[]}],"moveFrequency":3,"moveRoute":{"list":[{"code":0,"parameters":[]}],"repeat":true,"skippable":false,"wait":false},"moveSpeed":3,"moveType":0,"priorityType":0,"stepAnime":false,"through":false,"trigger":0,"walkAnime":true}],"x":16,"y":12},
{"id":3,"name":"EV003","note":"","pages":[{"conditions":{"actorId":1,"actorValid":false,"itemId":1,"itemValid":false,"selfSwitchCh":"A","selfSwitchValid":false,"switch1Id":9,"switch1Valid":true,"switch2Id":1,"switch2Valid":false,"variableId":1,"variableValid":false,"variableValue":0},"directionFix":false,"image":{"characterIndex":0,"characterName":"","direction":2,"pattern":0,"tileId":0},"list":[{"code":122,"indent":0,"parameters":[10,10,0,4,"TouchInput._x;(TouchInput.x);"]},{"code":122,"indent":0,"parameters":[11,11,0,4,"TouchInput._y;(TouchInput.y);"]},{"code":111,"indent":0,"parameters":[12,"TouchInput.isTriggered()"]},{"code":356,"indent":1,"parameters":["Show_Animation \\v[10] \\v[11] 2"]},{"code":0,"indent":1,"parameters":[]},{"code":412,"indent":0,"parameters":[]},{"code":0,"indent":0,"parameters":[]}],"moveFrequency":3,"moveRoute":{"list":[{"code":0,"parameters":[]}],"repeat":true,"skippable":false,"wait":false},"moveSpeed":3,"moveType":0,"priorityType":0,"stepAnime":false,"through":false,"trigger":4,"walkAnime":true}],"x":16,"y":0},
null
]
}